torchbenchmark/__init__.py
torchbenchmark/estimator/__init__.py
torchbenchmark/estimator/model_estimator.py
torchbenchmark/estimator/pytorch_estimator.py
torchbenchmark/estimator/pytorch_modelsize.py
torchbenchmark/estimator/sequential_model_estimator.py
torchbenchmark/network/__init__.py
torchbenchmark/network/core/AlexNet.py
torchbenchmark/network/core/__init__.py
torchbenchmark-0.0.7.dist-info/LICENSE
torchbenchmark-0.0.7.dist-info/METADATA
torchbenchmark-0.0.7.dist-info/WHEEL
torchbenchmark-0.0.7.dist-info/top_level.txt
torchbenchmark-0.0.7.dist-info/RECORD
